hydra_plugins/__init__.py
hydra_plugins/tempor_searchpath_plugin.py
tempor/__init__.py
tempor/automl/__init__.py
tempor/automl/_types.py
tempor/automl/pipeline_selector.py
tempor/automl/seeker.py
tempor/automl/tuner.py
tempor/benchmarks/__init__.py
tempor/benchmarks/benchmark.py
tempor/benchmarks/evaluation.py
tempor/benchmarks/utils.py
tempor/config/__init__.py
tempor/config/conf/__init__.py
tempor/config/conf/tempor/__init__.py
tempor/config/conf/tempor/config.yaml
tempor/core/__init__.py
tempor/core/pydantic_utils.py
tempor/core/types.py
tempor/core/utils.py
tempor/core/plugins/__init__.py
tempor/core/plugins/_utils.py
tempor/core/plugins/plugin_typing.py
tempor/data/__init__.py
tempor/data/clv2conv.py
tempor/data/data_typing.py
tempor/data/dataset.py
tempor/data/pandera_utils.py
tempor/data/predictive.py
tempor/data/samples.py
tempor/data/samples_experimental.py
tempor/data/settings.py
tempor/data/utils.py
tempor/datasources/__init__.py
tempor/datasources/datasource.py
tempor/datasources/prediction/__init__.py
tempor/datasources/prediction/one_off/__init__.py
tempor/datasources/prediction/one_off/plugin_google_stocks.py
tempor/datasources/prediction/one_off/plugin_sine.py
tempor/datasources/prediction/temporal/__init__.py
tempor/datasources/prediction/temporal/plugin_dummy_prediction.py
tempor/datasources/prediction/temporal/plugin_uci_diabetes.py
tempor/datasources/time_to_event/__init__.py
tempor/datasources/time_to_event/plugin_pbc.py
tempor/datasources/treatments/__init__.py
tempor/datasources/treatments/one_off/__init__.py
tempor/datasources/treatments/one_off/plugin_pkpd.py
tempor/datasources/treatments/temporal/__init__.py
tempor/datasources/treatments/temporal/plugin_dummy_treatments.py
tempor/exc/__init__.py
tempor/log/__init__.py
tempor/log/_custom_logger.py
tempor/log/log_helpers.py
tempor/methods/__init__.py
tempor/methods/constants.py
tempor/methods/core/__init__.py
tempor/methods/core/_base_estimator.py
tempor/methods/core/_base_predictor.py
temporai-0.0.3.dist-info/LICENSE.txt
temporai-0.0.3.dist-info/METADATA
temporai-0.0.3.dist-info/WHEEL
temporai-0.0.3.dist-info/top_level.txt
temporai-0.0.3.dist-info/RECORD
