Metadata-Version: 2.1
Name: temporai
Version: 0.0.3
Summary: TemporAI: ML-centric Toolkit for Medical Time Series
Home-page: https://github.com/vanderschaarlab/temporai
Author: Evgeny Saveliev
Author-email: e.s.saveliev@gmail.com
License: Apache-2.0 license
Project-URL: Documentation, https://temporai.readthedocs.io/en/latest/
Project-URL: Source, https://github.com/vanderschaarlab/temporai
Project-URL: Changelog, https://github.com/vanderschaarlab/temporai/releases
Project-URL: Tracker, https://github.com/vanderschaarlab/temporai/issues
Platform: any
Classifier: Development Status :: 3 - Alpha
Classifier: Intended Audience :: Developers
Classifier: Intended Audience :: Healthcare Industry
Classifier: Intended Audience :: Science/Research
Classifier: License :: OSI Approved :: Apache Software License
Classifier: Operating System :: OS Independent
Classifier: Programming Language :: Python :: 3
Classifier: Topic :: Scientific/Engineering :: Artificial Intelligence
Classifier: Topic :: Scientific/Engineering :: Medical Science Apps.
Classifier: Topic :: Software Development :: Libraries
Requires-Python: >=3.7
License-File: LICENSE.txt
Requires-Dist: clairvoyance2 >=0.0.2
Requires-Dist: cloudpickle
Requires-Dist: cmaes
Requires-Dist: dask[dataframe]
Requires-Dist: geomloss >=0.2.6
Requires-Dist: hydra-core >=1.3
Requires-Dist: hyperimpute >=0.1.17
Requires-Dist: lifelines !=0.27.5
Requires-Dist: loguru
Requires-Dist: numpy >=1
Requires-Dist: optuna >=2.8.0
Requires-Dist: packaging
Requires-Dist: pandas >=1
Requires-Dist: pandera >=0.17.0
Requires-Dist: pydantic >=2
Requires-Dist: rich
Requires-Dist: scikit-learn >=1.0
Requires-Dist: scipy
Requires-Dist: seaborn
Requires-Dist: torch
Requires-Dist: torchcde
Requires-Dist: torchdiffeq
Requires-Dist: torchlaplace >=0.0.4
Requires-Dist: tsai
Requires-Dist: typing-extensions >=4.7.1
Requires-Dist: xgbse
Requires-Dist: joblib ; python_version != "3.7" or platform_system != "Windows"
Requires-Dist: importlib-metadata ; python_version < "3.8"
Requires-Dist: joblib <1.3.0 ; python_version == "3.7" and platform_system == "Windows"
Provides-Extra: dev
Requires-Dist: black[jupyter] ; extra == 'dev'
Requires-Dist: blacken-docs ; extra == 'dev'
Requires-Dist: jupyter ; extra == 'dev'
Requires-Dist: myst-parser ; extra == 'dev'
Requires-Dist: nbsphinx ; extra == 'dev'
Requires-Dist: pyscaffold ; extra == 'dev'
Requires-Dist: pyscaffoldext-markdown >=0.5 ; extra == 'dev'
Requires-Dist: sphinx !=5.1.0,>=5 ; extra == 'dev'
Requires-Dist: sphinx-immaterial ; extra == 'dev'
Requires-Dist: pre-commit ; extra == 'dev'
Requires-Dist: pytest ; extra == 'dev'
Requires-Dist: pytest-cov ; extra == 'dev'
Requires-Dist: pytest-xdist ; extra == 'dev'
Requires-Dist: build ; extra == 'dev'
Requires-Dist: flake8 ; extra == 'dev'
Requires-Dist: isort ; extra == 'dev'
Requires-Dist: mypy >=1.0.0 ; extra == 'dev'
Requires-Dist: pylint ; extra == 'dev'
Requires-Dist: pydoclint ; extra == 'dev'
Requires-Dist: pydocstyle ; extra == 'dev'
Requires-Dist: setuptools ; extra == 'dev'
Requires-Dist: setuptools-scm ; extra == 'dev'
Requires-Dist: tox ; extra == 'dev'
Requires-Dist: twine ; extra == 'dev'
Provides-Extra: docs
Requires-Dist: black[jupyter] ; extra == 'docs'
Requires-Dist: blacken-docs ; extra == 'docs'
Requires-Dist: jupyter ; extra == 'docs'
Requires-Dist: myst-parser ; extra == 'docs'
Requires-Dist: nbsphinx ; extra == 'docs'
Requires-Dist: pyscaffold ; extra == 'docs'
Requires-Dist: pyscaffoldext-markdown >=0.5 ; extra == 'docs'
Requires-Dist: sphinx !=5.1.0,>=5 ; extra == 'docs'
Requires-Dist: sphinx-immaterial ; extra == 'docs'
Provides-Extra: testing
Requires-Dist: black[jupyter] ; extra == 'testing'
Requires-Dist: blacken-docs ; extra == 'testing'
Requires-Dist: jupyter ; extra == 'testing'
Requires-Dist: myst-parser ; extra == 'testing'
Requires-Dist: nbsphinx ; extra == 'testing'
Requires-Dist: pyscaffold ; extra == 'testing'
Requires-Dist: pyscaffoldext-markdown >=0.5 ; extra == 'testing'
Requires-Dist: sphinx !=5.1.0,>=5 ; extra == 'testing'
Requires-Dist: sphinx-immaterial ; extra == 'testing'
Requires-Dist: pre-commit ; extra == 'testing'
Requires-Dist: pytest ; extra == 'testing'
Requires-Dist: pytest-cov ; extra == 'testing'
Requires-Dist: pytest-xdist ; extra == 'testing'
